taskpath/.env.development
taskpath/.env.production
taskpath/__init__.py
taskpath/eslint.config.js
taskpath/index.html
taskpath/package-lock.json
taskpath/package.json
taskpath/privacy-policy.md
taskpath/tsconfig.app.json
taskpath/tsconfig.json
taskpath/tsconfig.node.json
taskpath/vite.config.ts
taskpath/dist/index.html
taskpath/dist/taskpath-logo.webp
taskpath/dist/taskpath.webp
taskpath/dist/assets/index-2Tnr-VAI.css
taskpath/dist/assets/index-BK2hQRRA.js
taskpath/public/taskpath-logo.webp
taskpath/public/taskpath.webp
taskpath/src/App.tsx
taskpath/src/AuthContext.tsx
taskpath/src/Footer.tsx
taskpath/src/Header.tsx
taskpath/src/Layout.tsx
taskpath/src/Navigation.tsx
taskpath/src/global.css
taskpath/src/global.d.ts
taskpath/src/main.tsx
taskpath/src/privateRoutes.tsx
taskpath/src/utils.ts
taskpath/src/vite-env.d.ts
taskpath/src/components/PrivateRoute.tsx
taskpath/src/components/PublicRoute.tsx
taskpath/src/components/Task.css
taskpath/src/components/Task.tsx
taskpath/src/pages/CheckEmail.tsx
taskpath/src/pages/ContactUs.tsx
taskpath/src/pages/HowItWorks.tsx
taskpath/src/pages/LandingPage.css
taskpath/src/pages/LandingPage.tsx
taskpath/src/pages/PrivacyPolicy.tsx
taskpath/src/pages/SignIn.tsx
taskpath/src/pages/SignUp.tsx
taskpath/src/pages/SignedIn.tsx
taskpath/src/pages/projects/Create.tsx
taskpath/src/pages/projects/List.tsx
taskpath/src/pages/projects/Read.tsx
taskpath-0.0.17.dist-info/METADATA
taskpath-0.0.17.dist-info/WHEEL
taskpath-0.0.17.dist-info/entry_points.txt
taskpath-0.0.17.dist-info/licenses/LICENSE
taskpath-0.0.17.dist-info/RECORD
